[{"id": 392, "point_a": [-13376.0, 6664.0, -3712.0], "point_b": [-11210.0, 8696.0, -2686.0], "target": "endzone", "track": 0, "type": "end"}, {"id": 393, "point_a": [-13120.0, -4928.0, 14976.0], "point_b": [-11200.0, -3008.0, 15682.0], "target": "startzone", "track": 0, "type": "start"}, {"id": 401, "point_a": [10304.0, -10688.0, -2304.0], "point_b": [10688.0, -10304.0, -2046.0], "target": "bonus_start", "track": 1, "type": "start"}, {"id": 402, "point_a": [10304.0, -10688.0, -2304.0], "point_b": [10688.0, -10304.0, -2046.0], "target": "bonus_start", "track": 1, "type": "start"}, {"id": 403, "point_a": [15600.0, -10880.0, -13135.96875], "point_b": [16064.0, -10112.0, -12160.0], "track": 1, "type": "end"}, {"id": 404, "point_a": [10112.0, -16064.0, -13135.96875], "point_b": [10880.0, -15600.0, -12160.0], "track": 1, "type": "end"}, {"id": 405, "point_a": [4928.0, -10880.0, -13135.96875], "point_b": [5392.0, -10112.0, -12156.0], "track": 1, "type": "end"}, {"id": 406, "point_a": [10112.0, -5392.0, -13135.96875], "point_b": [10880.0, -4928.0, -12160.0], "track": 1, "type": "end"}, {"data": 1, "id": 823, "point_a": [11264.0, -8672.0, 5760.0], "point_b": [12032.0, 240.0, 10943.9111328125], "track": 0, "type": "checkpoint"}, {"data": 2, "id": 824, "point_a": [3568.0, -1280.0, 3040.0], "point_b": [4608.0, 4352.0, 7046.73193359375], "track": 0, "type": "checkpoint"}]